pharia_studio_sdk/__init__.py
pharia_studio_sdk/py.typed
pharia_studio_sdk/connectors/__init__.py
pharia_studio_sdk/connectors/argilla/argilla_client.py
pharia_studio_sdk/connectors/argilla/argilla_wrapper_client.py
pharia_studio_sdk/connectors/base/json_serializable.py
pharia_studio_sdk/connectors/studio/studio.py
pharia_studio_sdk/evaluation/__init__.py
pharia_studio_sdk/evaluation/run_evaluation.py
pharia_studio_sdk/evaluation/aggregation/accumulator.py
pharia_studio_sdk/evaluation/aggregation/aggregation_repository.py
pharia_studio_sdk/evaluation/aggregation/aggregator.py
pharia_studio_sdk/evaluation/aggregation/domain.py
pharia_studio_sdk/evaluation/aggregation/elo_aggregation.py
pharia_studio_sdk/evaluation/aggregation/file_aggregation_repository.py
pharia_studio_sdk/evaluation/aggregation/hugging_face_aggregation_repository.py
pharia_studio_sdk/evaluation/aggregation/in_memory_aggregation_repository.py
pharia_studio_sdk/evaluation/benchmark/benchmark.py
pharia_studio_sdk/evaluation/benchmark/get_code.py
pharia_studio_sdk/evaluation/benchmark/studio_benchmark.py
pharia_studio_sdk/evaluation/benchmark/trace_information.py
pharia_studio_sdk/evaluation/dataset/dataset_repository.py
pharia_studio_sdk/evaluation/dataset/domain.py
pharia_studio_sdk/evaluation/dataset/file_dataset_repository.py
pharia_studio_sdk/evaluation/dataset/hugging_face_dataset_repository.py
pharia_studio_sdk/evaluation/dataset/in_memory_dataset_repository.py
pharia_studio_sdk/evaluation/dataset/single_huggingface_dataset_repository.py
pharia_studio_sdk/evaluation/dataset/studio_dataset_repository.py
pharia_studio_sdk/evaluation/evaluation/__init__.py
pharia_studio_sdk/evaluation/evaluation/domain.py
pharia_studio_sdk/evaluation/evaluation/evaluation_repository.py
pharia_studio_sdk/evaluation/evaluation/file_evaluation_repository.py
pharia_studio_sdk/evaluation/evaluation/graders.py
pharia_studio_sdk/evaluation/evaluation/in_memory_evaluation_repository.py
pharia_studio_sdk-0.1.7.dist-info/METADATA
pharia_studio_sdk-0.1.7.dist-info/WHEEL
pharia_studio_sdk-0.1.7.dist-info/licenses/LICENSE
pharia_studio_sdk-0.1.7.dist-info/licenses/NOTICE.md
pharia_studio_sdk-0.1.7.dist-info/RECORD
