Metadata-Version: 2.4
Name: pharia-studio-sdk
Version: 0.1.7
Project-URL: repository, https://github.com/Aleph-Alpha/pharia-studio-sdk.git
Author-email: Aleph Alpha Engineering <engineering@aleph-alpha.com>
License-File: LICENSE
License-File: NOTICE.md
Requires-Python: <3.13,>=3.10
Requires-Dist: aleph-alpha-client<11.0.0,>=10.2.2
Requires-Dist: argilla>=2.8.0
Requires-Dist: datasets>=3.6.0
Requires-Dist: dict-hash>=1.3.6
Requires-Dist: huggingface-hub>=0.32.6
Requires-Dist: pharia-inference-sdk>=0.1.5
Requires-Dist: pydantic>=2.11.5
Requires-Dist: rouge-score>=0.1.2
Requires-Dist: sacrebleu>=2.5.1
